Metadata-Version: 1.1
Name: ytdlraw
Version: 0.2.1
Summary: A barebones YouTube Downloader
Home-page: UNKNOWN
Author: DS_Stift007
Author-email: dsstif@icloud.org
License: MIT
Keywords: youtube,download,ytdl
Platform: UNKNOWN
Classifier: Development Status :: 5 - Production/Stable
Classifier: Intended Audience :: Education
Classifier: Operating System :: Microsoft :: Windows :: Windows 10 
Classifier: License :: OSI Approved :: MIT License
Classifier: Programming Language :: Python :: 3
